basis/__init__.py
basis/api.py
basis/cli/__init__.py
basis/cli/app.py
basis/cli/commands/__init__.py
basis/cli/commands/base.py
basis/cli/commands/generate.py
basis/cli/commands/output.py
basis/cli/commands/run.py
basis/core/__init__.py
basis/core/component.py
basis/core/data_block.py
basis/core/declarative/__init__.py
basis/core/declarative/base.py
basis/core/declarative/dataspace.py
basis/core/declarative/execution.py
basis/core/declarative/flow.py
basis/core/declarative/function.py
basis/core/declarative/graph.py
basis/core/declarative/interface.py
basis/core/environment.py
basis/core/execution/__init__.py
basis/core/execution/context.py
basis/core/execution/execution.py
basis/core/execution/run.py
basis/core/extraction/__init__.py
basis/core/extraction/connection.py
basis/core/flattener.py
basis/core/function.py
basis/core/function_interface.py
basis/core/function_interface_manager.py
basis/core/function_package.py
basis/core/module.py
basis/core/operators.py
basis/core/persistence/__init__.py
basis/core/persistence/api.py
basis/core/persistence/base.py
basis/core/persistence/data_block.py
basis/core/persistence/pydantic.py
basis/core/persistence/schema.py
basis/core/persistence/state.py
basis/core/runtime.py
basis/core/sql/__init__.py
basis/core/sql/parser.py
basis/core/sql/sql_function.py
basis/core/storage.py
basis/core/typing/__init__.py
basis/core/typing/casting.py
basis/core/typing/inference.py
basis/helpers/__init__.py
basis/helpers/connectors/README.md
basis/helpers/connectors/__init__.py
basis/helpers/connectors/connection.py
basis/helpers/connectors/mock_data_source.py
basis/helpers/connectors/response.py
basis/logging/__init__.py
basis/migrations/README
basis/migrations/alembic.ini
basis/migrations/env.py
basis/migrations/script.py.mako
basis/migrations/versions/5e787d339651_initial_migration.py
basis/migrations/versions/722cbaa0a8d2_node_state.py
basis/migrations/versions/83486b160cf0_alias_storage_url.py
basis_core-0.1.0.dist-info/entry_points.txt
basis_core-0.1.0.dist-info/LICENSE
basis_core-0.1.0.dist-info/WHEEL
basis_core-0.1.0.dist-info/METADATA
basis_core-0.1.0.dist-info/RECORD
